<?xml version="1.0" encoding="utf-8" ?>
<programmes>
  <programme name="ABIME DE LA PASSION Episode" start="01:00:00" end="01:46:17" url="serie"></programme>
  <programme name="GEN-PUB" start="01:46:17" end="01:46:29" url="youtube:Vbev5Vsi_4w"></programme>
  <programme name="PUB-SAC-FASHION" start="01:46:29" end="01:48:49" url="youtube:GlGLnTXH_ik"></programme>
  <programme name="PUB-CHEMISE-FASHION" start="01:48:49" end="01:50:37" url="youtube:X0WGkOPLU5c"></programme>
  <programme name="DOUBLE JEUX" start="01:50:37" end="02:36:23" url="serie"></programme>
  <programme name="GEN-PUB" start="02:36:23" end="02:36:55" url="youtube:Vbev5Vsi_4w"></programme>
  <programme name="PUB-ROBE-FASHION" start="02:36:23" end="02:38:18" url="youtube:GlGLnTXH_ik"></programme>
  <programme name="PUB-CHAUSSURE-FASHION" start="02:38:18" end="02:40:10" url="youtube:yORIAPoLSAE"></programme>
  <programme name="GEN-MPAKA" start="02:40:10" end="02:40:48" url="youtube:e36xg4ThoJg"></programme>
  <programme name="MUSIQUE-PL" start="02:40:48" end="02:59:03" url="youtube-pl:PL3ICd40lrnu_oEn2ZC7536aJB060KxfSB"></programme>
  <programme name="GEN-PUB" start="02:59:03" end="02:59:15" url="youtube:Vbev5Vsi_4w"></programme>
  <programme name="PUB-SAC-FASHION" start="02:59:15" end="03:01:35" url="youtube:GlGLnTXH_ik"></programme>
  <programme name="GEN-MPAKA" start="03:01:35" end="03:02:13" url="youtube:e36xg4ThoJg"></programme>
  <programme name="PUB-CHAUSSURE-FASHION" start="03:02:13" end="03:04:06" url="youtube:yORIAPoLSAE"></programme>
  <programme name="EL DIABLO" start="03:04:06" end="03:46:56" url="serie"></programme>
  <programme name="GEN-PUB" start="03:46:56" end="03:47:08" url="youtube:Vbev5Vsi_4w"></programme>
  <programme name="PUB-ROBE-FASHION" start="03:47:08" end="03:49:04" url="youtube:GlGLnTXH_ik"></programme>
  <programme name="GEN-MPAKA" start="03:49:04" end="03:49:42" url="youtube:e36xg4ThoJg"></programme>
  <programme name="PUB-CHEMISE-FASHION" start="03:49:42" end="03:51:30" url="youtube:X0WGkOPLU5c"></programme>
  <programme name="MUSIQUE-PL" start="03:51:30" end="04:10:30" url="youtube-pl:PL3ICd40lrnu9kD_26H_DbuxG5QDdFNvEl"></programme>
  <programme name="GEN-PUB" start="04:10:30" end="04:10:42" url="youtube:Vbev5Vsi_4w"></programme>
  <programme name="PUB-ROBE-FASHION" start="04:10:42" end="04:12:38" url="youtube:GlGLnTXH_ik"></programme>
  <programme name="GEN-MPAKA" start="04:12:38" end="04:13:16" url="youtube:e36xg4ThoJg"></programme>
  <programme name="PUB-CHAUSSURE-FASHION" start="04:13:16" end="04:15:09" url="youtube:yORIAPoLSAE"></programme>
  <programme name="AU NOM DE LA VERITE" start="04:15:09" end="04:39:21" url="serie"></programme>
  <programme name="GEN-PUB" start="04:39:21" end="04:39:33" url="youtube:Vbev5Vsi_4w"></programme>
  <programme name="PUB-ROBE-FASHION" start="04:39:33" end="04:41:29" url="youtube:GlGLnTXH_ik"></programme>
  <programme name="GEN-MPAKA" start="04:41:29" end="04:42:07" url="youtube:e36xg4ThoJg"></programme>
  <programme name="PUB-CHAUSSURE-FASHION" start="04:42:07" end="04:44:00" url="youtube:yORIAPoLSAE"></programme>
  <programme name="HOROSCOPE HEBDOMADAIRE" start="04:44:00" end="04:49:00" url="youtube-pl:PL3ICd40lrnu-TgfAnWPf0kyr5-b2SS-YD"></programme>
  <programme name="GEN-PUB" start="04:49:00" end="04:49:30" url="youtube:Vbev5Vsi_4w"></programme>
  <programme name="PUB-ROBE-FASHION" start="04:49:30" end="04:51:26" url="youtube:GlGLnTXH_ik"></programme>
  <programme name="GEN-MPAKA" start="04:51:26" end="04:52:04" url="youtube:e36xg4ThoJg"></programme>
  <programme name="PUB-CHAUSSURE-FASHION" start="04:52:04" end="04:53:57" url="youtube:yORIAPoLSAE"></programme>
  <programme name="GEN-PUB" start="04:56:57" end="04:57:35" url="youtube:Vbev5Vsi_4w"></programme>
  <programme name="PUB-CHEMISE-FASHION" start="04:57:35" end="04:59:23" url="youtube:X0WGkOPLU5c"></programme>
  <programme name="GEN-MPAKA" start="04:59:23" end="05:00:01" url="youtube:e36xg4ThoJg"></programme>
  <programme name="PUB-SAC-FASHION" start="05:00:01" end="05:02:21" url="youtube:GlGLnTXH_ik"></programme>
  <programme name="LA REINE DU SHOPPING" start="05:02:01" end="05:53:15" url="serie"></programme>
  <programme name="GEN-PUB" start="05:53:15" end="05:53:27" url="youtube:Vbev5Vsi_4w"></programme>
  <programme name="PUB-ROBE-FASHION" start="05:53:27" end="05:55:11" url="youtube:GlGLnTXH_ik"></programme>
  <programme name="METEO" start="05:55:11" end="05:57:00" url="youtube-pl:PL3ICd40lrnu9AzoHw791hn2THm3PPiYWo"></programme>
  <programme name="ANNONCES" start="05:57:00" end="06:00:00" url="youtube:GlGLnTXH_ik"></programme>

  <programme name="ABIME DE LA PASSION Episode" start="06:00:00" end="06:46:17" url="serie"></programme>
  <programme name="GEN-PUB" start="06:46:17" end="06:46:29" url="youtube:Vbev5Vsi_4w"></programme>
  <programme name="PUB-SAC-FASHION" start="06:46:29" end="06:48:49" url="youtube:GlGLnTXH_ik"></programme>
  <programme name="PUB-CHEMISE-FASHION" start="06:48:49" end="06:50:37" url="youtube:X0WGkOPLU5c"></programme>
  <programme name="DOUBLE JEUX" start="06:50:37" end="07:36:23" url="serie"></programme>
  <programme name="GEN-PUB" start="07:36:23" end="07:36:55" url="youtube:Vbev5Vsi_4w"></programme>
  <programme name="PUB-ROBE-FASHION" start="07:36:23" end="07:38:18" url="youtube:GlGLnTXH_ik"></programme>
  <programme name="PUB-CHAUSSURE-FASHION" start="07:38:18" end="07:40:10" url="youtube:yORIAPoLSAE"></programme>
  <programme name="GEN-MPAKA" start="07:40:10" end="07:40:48" url="youtube:e36xg4ThoJg"></programme>
  <programme name="MUSIQUE-PL" start="07:40:48" end="07:59:03" url="youtube-pl:PL3ICd40lrnu_g1CRL4TvpkUBAU1CsoziS"></programme>
  <programme name="GEN-PUB" start="07:59:03" end="07:59:15" url="youtube:Vbev5Vsi_4w"></programme>
  <programme name="PUB-SAC-FASHION" start="07:59:15" end="08:01:35" url="youtube:GlGLnTXH_ik"></programme>
  <programme name="GEN-MPAKA" start="08:01:35" end="08:02:13" url="youtube:e36xg4ThoJg"></programme>
  <programme name="PUB-CHAUSSURE-FASHION" start="08:02:13" end="08:04:06" url="youtube:yORIAPoLSAE"></programme>
  <programme name="EL DIABLO" start="08:04:06" end="08:46:56" url="serie"></programme>
  <programme name="GEN-PUB" start="08:46:56" end="08:47:08" url="youtube:Vbev5Vsi_4w"></programme>
  <programme name="PUB-ROBE-FASHION" start="08:47:08" end="08:49:04" url="youtube:GlGLnTXH_ik"></programme>
  <programme name="GEN-MPAKA" start="08:49:04" end="08:49:42" url="youtube:e36xg4ThoJg"></programme>
  <programme name="PUB-CHEMISE-FASHION" start="08:49:42" end="08:51:30" url="youtube:X0WGkOPLU5c"></programme>
  <programme name="MUSIQUE-PL" start="08:51:30" end="09:10:30" url="youtube-pl:PL3ICd40lrnu9dBt8CoD_oSAuOhmUMukQy"></programme>
  <programme name="GEN-PUB" start="09:10:30" end="09:10:42" url="youtube:lMTkpj62Vbg"></programme>
  <programme name="PUB-ROBE-FASHION" start="09:10:42" end="09:12:38" url="youtube:GlGLnTXH_ik"></programme>
  <programme name="GEN-MPAKA" start="09:12:38" end="09:13:16" url="youtube:e36xg4ThoJg"></programme>
  <programme name="PUB-CHAUSSURE-FASHION" start="09:13:16" end="09:15:09" url="youtube:yORIAPoLSAE"></programme>
  <programme name="AU NOM DE LA VERITE" start="09:15:09" end="09:39:21" url="serie"></programme>
  <programme name="GEN-PUB" start="09:39:21" end="09:39:33" url="youtube:Vbev5Vsi_4w"></programme>
  <programme name="PUB-ROBE-FASHION" start="09:39:33" end="09:41:29" url="youtube:GlGLnTXH_ik"></programme>
  <programme name="GEN-MPAKA" start="09:41:29" end="09:42:07" url="youtube:e36xg4ThoJg"></programme>
  <programme name="PUB-CHAUSSURE-FASHION" start="09:42:07" end="09:44:00" url="youtube:yORIAPoLSAE"></programme>
  <programme name="HOROSCOPE HEBDOMADAIRE" start="09:44:00" end="09:49:00" url="youtube-pl:PL3ICd40lrnu-TgfAnWPf0kyr5-b2SS-YD"></programme>
  <programme name="GEN-PUB" start="09:49:00" end="09:49:30" url="youtube:Vbev5Vsi_4w"></programme>
  <programme name="PUB-ROBE-FASHION" start="09:49:30" end="09:51:26" url="youtube:GlGLnTXH_ik"></programme>
  <programme name="GEN-MPAKA" start="09:51:26" end="09:52:04" url="youtube:e36xg4ThoJg"></programme>
  <programme name="PUB-CHAUSSURE-FASHION" start="09:52:04" end="09:53:57" url="youtube:yORIAPoLSAE"></programme>
  <programme name="GEN-PUB" start="09:56:57" end="09:57:35" url="youtube:Vbev5Vsi_4w"></programme>
  <programme name="PUB-CHEMISE-FASHION" start="09:57:35" end="09:59:23" url="youtube:X0WGkOPLU5c"></programme>
  <programme name="GEN-MPAKA" start="09:59:23" end="10:00:01" url="youtube:e36xg4ThoJg"></programme>
  <programme name="PUB-SAC-FASHION" start="10:00:01" end="10:02:21" url="youtube:GlGLnTXH_ik"></programme>
  <programme name="LA REINE DU SHOPPING" start="10:02:01" end="10:53:15" url="serie"></programme>
  <programme name="GEN-PUB" start="10:53:15" end="10:53:27" url="youtube:Vbev5Vsi_4w"></programme>
  <programme name="PUB-ROBE-FASHION" start="10:53:27" end="10:55:11" url="youtube:GlGLnTXH_ik"></programme>
  <programme name="QUIZZ" start="10:55:11" end="10:57:00" url="quizz"></programme>
  <programme name="ANNONCES" start="10:57:00" end="11:00:00" url="youtube:GlGLnTXH_ik"></programme>

  <programme name="ABIME DE LA PASSION Episode" start="11:00:00" end="11:46:17" url="serie"></programme>
  <programme name="GEN-PUB" start="11:46:17" end="11:46:29" url="youtube:Vbev5Vsi_4w"></programme>
  <programme name="PUB-SAC-FASHION" start="11:46:29" end="11:48:49" url="youtube:GlGLnTXH_ik"></programme>
  <programme name="PUB-CHEMISE-FASHION" start="11:48:49" end="11:50:37" url="youtube:X0WGkOPLU5c"></programme>
  <programme name="DOUBLE JEUX" start="11:50:37" end="12:36:23" url="serie"></programme>
  <programme name="GEN-PUB" start="12:36:23" end="12:36:55" url="youtube:Vbev5Vsi_4w"></programme>
  <programme name="PUB-ROBE-FASHION" start="12:36:23" end="12:38:18" url="youtube:GlGLnTXH_ik"></programme>
  <programme name="PUB-CHAUSSURE-FASHION" start="12:38:18" end="12:40:10" url="youtube:yORIAPoLSAE"></programme>
  <programme name="GEN-MPAKA" start="12:40:10" end="12:40:48" url="youtube:e36xg4ThoJg"></programme>
  <programme name="MUSIQUE-PL" start="12:40:48" end="12:59:03" url="youtube-pl:PL3ICd40lrnu-soKvtPnjzDNHAOjFsrEsQ"></programme>
  <programme name="GEN-PUB" start="12:59:03" end="12:59:15" url="youtube:Vbev5Vsi_4w"></programme>
  <programme name="PUB-SAC-FASHION" start="12:59:15" end="13:01:35" url="youtube:GlGLnTXH_ik"></programme>
  <programme name="GEN-MPAKA" start="13:01:35" end="13:02:13" url="youtube:e36xg4ThoJg"></programme>
  <programme name="PUB-CHAUSSURE-FASHION" start="13:02:13" end="13:04:06" url="youtube:yORIAPoLSAE"></programme>
  <programme name="EL DIABLO" start="13:04:06" end="13:46:56" url="serie"></programme>
  <programme name="GEN-PUB" start="13:46:56" end="13:47:08" url="youtube:Vbev5Vsi_4w"></programme>
  <programme name="PUB-ROBE-FASHION" start="13:47:08" end="13:49:04" url="youtube:GlGLnTXH_ik"></programme>
  <programme name="GEN-MPAKA" start="13:49:04" end="13:49:42" url="youtube:e36xg4ThoJg"></programme>
  <programme name="PUB-CHEMISE-FASHION" start="13:49:42" end="13:51:30" url="youtube:X0WGkOPLU5c"></programme>
  <programme name="MUSIQUE-PL" start="13:51:30" end="14:10:30" url="youtube-pl:PL3ICd40lrnu9IEJc7YpD0JTVE7py5CNAw"></programme>
  <programme name="GEN-PUB" start="14:10:30" end="14:10:42" url="youtube:Vbev5Vsi_4w"></programme>
  <programme name="PUB-ROBE-FASHION" start="14:10:42" end="14:12:38" url="youtube:GlGLnTXH_ik"></programme>
  <programme name="GEN-MPAKA" start="14:12:38" end="14:13:16" url="youtube:e36xg4ThoJg"></programme>
  <programme name="PUB-CHAUSSURE-FASHION" start="14:13:16" end="14:15:09" url="youtube:yORIAPoLSAE"></programme>
  <programme name="AU NOM DE LA VERITE" start="14:15:09" end="14:39:21" url="serie:aunomdelaverite.xml"></programme>
  <programme name="GEN-PUB" start="14:39:21" end="14:39:33" url="youtube:Vbev5Vsi_4w"></programme>
  <programme name="PUB-ROBE-FASHION" start="14:39:33" end="14:41:29" url="youtube:GlGLnTXH_ik"></programme>
  <programme name="GEN-MPAKA" start="14:41:29" end="14:42:07" url="youtube:e36xg4ThoJg"></programme>
  <programme name="PUB-CHAUSSURE-FASHION" start="14:42:07" end="14:44:00" url="youtube:yORIAPoLSAE"></programme>
  <programme name="HOROSCOPE HEBDOMADAIRE" start="14:44:00" end="14:49:00" url="youtube-pl:PL3ICd40lrnu-TgfAnWPf0kyr5-b2SS-YD"></programme>
  <programme name="GEN-PUB" start="14:49:00" end="14:49:30" url="youtube:Vbev5Vsi_4w"></programme>
  <programme name="PUB-ROBE-FASHION" start="14:49:30" end="14:51:26" url="youtube:GlGLnTXH_ik"></programme>
  <programme name="GEN-MPAKA" start="14:51:26" end="14:52:04" url="youtube:e36xg4ThoJg"></programme>
  <programme name="PUB-CHAUSSURE-FASHION" start="14:52:04" end="14:53:57" url="youtube:yORIAPoLSAE"></programme>
  <programme name="GEN-PUB" start="14:56:57" end="14:57:35" url="youtube:Vbev5Vsi_4w"></programme>
  <programme name="PUB-CHEMISE-FASHION" start="14:57:35" end="14:59:23" url="youtube:X0WGkOPLU5c"></programme>
  <programme name="GEN-MPAKA" start="14:59:23" end="15:00:01" url="youtube:e36xg4ThoJg"></programme>
  <programme name="PUB-SAC-FASHION" start="15:00:01" end="15:02:21" url="youtube:GlGLnTXH_ik"></programme>
  <programme name="LA FORCE DU COEUR" start="15:02:01" end="15:53:15" url="serie:lareinedushopping"></programme>
  <programme name="GEN-PUB" start="15:53:15" end="15:53:27" url="youtube:Vbev5Vsi_4w"></programme>
  <programme name="PUB-ROBE-FASHION" start="15:53:27" end="15:55:11" url="youtube:GlGLnTXH_ik"></programme>
  <programme name="QUIZZ" start="15:55:11" end="15:57:00" url="youtube:GlGLnTXH_ik"></programme>
  <programme name="ANNONCES" start="15:57:00" end="16:00:00" url="youtube:GlGLnTXH_ik"></programme>

  <programme name="ABIME DE LA PASSION Episode" start="16:00:00" end="16:46:17" url="serie"></programme>
  <programme name="GEN-PUB" start="16:46:17" end="16:46:29" url="youtube:Vbev5Vsi_4w"></programme>
  <programme name="PUB-SAC-FASHION" start="16:46:29" end="16:48:49" url="youtube:GlGLnTXH_ik"></programme>
  <programme name="PUB-CHEMISE-FASHION" start="16:48:49" end="16:50:37" url="youtube:X0WGkOPLU5c"></programme>
  <programme name="DOUBLE JEUX" start="16:50:37" end="17:36:23" url="serie"></programme>
  <programme name="GEN-PUB" start="17:36:23" end="17:36:55" url="youtube:Vbev5Vsi_4w"></programme>
  <programme name="PUB-ROBE-FASHION" start="17:36:23" end="17:38:18" url="youtube:GlGLnTXH_ik"></programme>
  <programme name="PUB-CHAUSSURE-FASHION" start="17:38:18" end="17:40:10" url="youtube:yORIAPoLSAE"></programme>
  <programme name="GEN-MPAKA" start="17:40:10" end="17:40:48" url="youtube:e36xg4ThoJg"></programme>
  <programme name="MUSIQUE-PL" start="17:40:48" end="17:59:03" url="youtube-pl:PL3ICd40lrnu-OSSkWHq08zJ425uGfmZpu"></programme>
  <programme name="GEN-PUB" start="17:59:03" end="17:59:15" url="youtube:Vbev5Vsi_4w"></programme>
  <programme name="PUB-SAC-FASHION" start="17:59:15" end="18:01:35" url="youtube:GlGLnTXH_ik"></programme>
  <programme name="GEN-MPAKA" start="18:01:35" end="18:02:13" url="youtube:e36xg4ThoJg"></programme>
  <programme name="PUB-CHAUSSURE-FASHION" start="18:02:13" end="18:04:06" url="youtube:yORIAPoLSAE"></programme>
  <programme name="EL DIABLO" start="18:04:06" end="18:46:56" url="serie:rubi.xml"></programme>
  <programme name="GEN-PUB" start="18:46:56" end="18:47:08" url="youtube:Vbev5Vsi_4w"></programme>
  <programme name="PUB-ROBE-FASHION" start="18:47:08" end="18:49:04" url="youtube:GlGLnTXH_ik"></programme>
  <programme name="GEN-MPAKA" start="18:49:04" end="18:49:42" url="youtube:e36xg4ThoJg"></programme>
  <programme name="PUB-CHEMISE-FASHION" start="18:49:42" end="18:51:30" url="youtube:X0WGkOPLU5c"></programme>
  <programme name="MUSIQUE-PL" start="18:51:30" end="19:10:30" url="youtube-pl:PL3ICd40lrnu9IEJc7YpD0JTVE7py5CNAw"></programme>
  <programme name="GEN-PUB" start="19:10:30" end="19:10:42" url="youtube:Vbev5Vsi_4w"></programme>
  <programme name="PUB-ROBE-FASHION" start="19:10:42" end="19:12:38" url="youtube:GlGLnTXH_ik"></programme>
  <programme name="GEN-MPAKA" start="19:12:38" end="19:13:16" url="youtube:e36xg4ThoJg"></programme>
  <programme name="PUB-CHAUSSURE-FASHION" start="19:13:16" end="19:15:09" url="youtube:yORIAPoLSAE"></programme>
  <programme name="AU NOM DE LA VERITE" start="19:15:09" end="19:39:21" url="serie:aunomdelaverite.xml"></programme>
  <programme name="GEN-PUB" start="19:39:21" end="19:39:33" url="youtube:Vbev5Vsi_4w"></programme>
  <programme name="PUB-ROBE-FASHION" start="19:39:33" end="19:41:29" url="youtube:GlGLnTXH_ik"></programme>
  <programme name="GEN-MPAKA" start="19:41:29" end="19:42:07" url="youtube:e36xg4ThoJg"></programme>
  <programme name="PUB-CHAUSSURE-FASHION" start="19:42:07" end="19:44:00" url="youtube:yORIAPoLSAE"></programme>
  <programme name="HOROSCOPE HEBDOMADAIRE" start="19:44:00" end="19:49:00" url="youtube-pl:PL3ICd40lrnu-TgfAnWPf0kyr5-b2SS-YD"></programme>
  <programme name="GEN-PUB" start="19:49:00" end="19:49:30" url="youtube:Vbev5Vsi_4w"></programme>
  <programme name="PUB-ROBE-FASHION" start="19:49:30" end="19:51:26" url="youtube:GlGLnTXH_ik"></programme>
  <programme name="GEN-MPAKA" start="19:51:26" end="19:52:04" url="youtube:e36xg4ThoJg"></programme>
  <programme name="PUB-CHAUSSURE-FASHION" start="19:52:04" end="19:53:57" url="youtube:yORIAPoLSAE"></programme>
  <programme name="GEN-PUB" start="19:56:57" end="19:57:35" url="youtube:Vbev5Vsi_4w"></programme>
  <programme name="PUB-CHEMISE-FASHION" start="19:57:35" end="19:59:23" url="youtube:X0WGkOPLU5c"></programme>
  <programme name="GEN-MPAKA" start="19:59:23" end="20:00:01" url="youtube:e36xg4ThoJg"></programme>
  <programme name="PUB-SAC-FASHION" start="20:00:01" end="20:02:21" url="youtube:GlGLnTXH_ik"></programme>
  <programme name="LA FORCE DU COEUR" start="20:02:01" end="20:53:15" url="serie:lareinedushopping"></programme>
  <programme name="GEN-PUB" start="20:53:15" end="20:53:27" url="youtube:Vbev5Vsi_4w"></programme>
  <programme name="PUB-ROBE-FASHION" start="20:53:27" end="20:55:11" url="youtube:GlGLnTXH_ik"></programme>
  <programme name="REPONSE_QUIZZ" start="20:55:11" end="20:57:00" url="REPONSE_QUIZZ"></programme>
  <programme name="ANNONCES" start="20:57:00" end="21:00:00" url="youtube:GlGLnTXH_ik"></programme>

  <programme name="ABIME DE LA PASSION Episode" start="21:00:00" end="21:46:17" url="serie"></programme>
  <programme name="GEN-PUB" start="21:46:17" end="21:46:29" url="youtube:Vbev5Vsi_4w"></programme>
  <programme name="PUB-SAC-FASHION" start="21:46:29" end="21:48:49" url="youtube:GlGLnTXH_ik"></programme>
  <programme name="PUB-CHEMISE-FASHION" start="21:48:49" end="21:50:37" url="youtube:X0WGkOPLU5c"></programme>
  <programme name="DOUBLE JEUX" start="21:50:37" end="22:36:23" url="serie"></programme>
  <programme name="GEN-PUB" start="22:36:23" end="22:36:55" url="youtube:Vbev5Vsi_4w"></programme>
  <programme name="PUB-ROBE-FASHION" start="22:36:23" end="22:38:18" url="youtube:GlGLnTXH_ik"></programme>
  <programme name="PUB-CHAUSSURE-FASHION" start="22:38:18" end="22:40:10" url="youtube:yORIAPoLSAE"></programme>
  <programme name="GEN-MPAKA" start="22:40:10" end="22:40:48" url="youtube:e36xg4ThoJg"></programme>
  <programme name="MUSIQUE-PL" start="22:40:48" end="22:59:03" url="youtube-pl:PL3ICd40lrnu_oEn2ZC7536aJB060KxfSB"></programme>
  <programme name="GEN-PUB" start="22:59:03" end="22:59:15" url="youtube:Vbev5Vsi_4w"></programme>
  <programme name="PUB-SAC-FASHION" start="22:59:15" end="23:01:35" url="youtube:GlGLnTXH_ik"></programme>
  <programme name="GEN-MPAKA" start="23:01:35" end="23:02:13" url="youtube:e36xg4ThoJg"></programme>
  <programme name="PUB-CHAUSSURE-FASHION" start="23:02:13" end="23:04:06" url="youtube:yORIAPoLSAE"></programme>
  <programme name="EL DIABLO" start="23:04:06" end="23:46:56" url="serie:rubi.xml"></programme>
  <programme name="GEN-PUB" start="23:46:56" end="23:47:08" url="youtube:Vbev5Vsi_4w"></programme>
  <programme name="PUB-ROBE-FASHION" start="23:47:08" end="23:49:04" url="youtube:GlGLnTXH_ik"></programme>
  <programme name="GEN-MPAKA" start="23:49:04" end="23:49:42" url="youtube:e36xg4ThoJg"></programme>
  <programme name="PUB-CHEMISE-FASHION" start="23:49:42" end="23:51:30" url="youtube:X0WGkOPLU5c"></programme>
  <programme name="MUSIQUE-PL" start="23:51:30" end="00:10:30" url="youtube-pl:PL3ICd40lrnu_g1CRL4TvpkUBAU1CsoziS"></programme>
  <programme name="GEN-PUB" start="00:10:30" end="00:10:42" url="youtube:Vbev5Vsi_4w"></programme>
  <programme name="PUB-ROBE-FASHION" start="00:10:42" end="00:12:38" url="youtube:GlGLnTXH_ik"></programme>
  <programme name="GEN-MPAKA" start="00:12:38" end="00:13:16" url="youtube:e36xg4ThoJg"></programme>
  <programme name="PUB-CHAUSSURE-FASHION" start="00:13:16" end="00:15:09" url="youtube:yORIAPoLSAE"></programme>
  <programme name="AU NOM DE LA VERITE" start="00:15:09" end="00:39:21" url="serie:aunomdelaverite.xml"></programme>
  <programme name="GEN-PUB" start="00:39:21" end="00:39:33" url="youtube:lMTkpj62Vbg"></programme>
  <programme name="PUB-ROBE-FASHION" start="00:39:33" end="00:41:29" url="youtube:GlGLnTXH_ik"></programme>
  <programme name="GEN-MPAKA" start="00:41:29" end="00:42:07" url="youtube:e36xg4ThoJg"></programme>
  <programme name="PUB-CHAUSSURE-FASHION" start="00:42:07" end="00:44:00" url="youtube:yORIAPoLSAE"></programme>
  <programme name="HOROSCOPE HEBDOMADAIRE" start="00:44:00" end="00:49:00" url="youtube-pl:PL3ICd40lrnu-TgfAnWPf0kyr5-b2SS-YD"></programme>
  <programme name="GEN-PUB" start="00:49:00" end="00:49:30" url="youtube:Vbev5Vsi_4w"></programme>
  <programme name="PUB-ROBE-FASHION" start="00:49:30" end="00:51:26" url="youtube:GlGLnTXH_ik"></programme>
  <programme name="GEN-MPAKA" start="00:51:26" end="00:52:04" url="youtube:e36xg4ThoJg"></programme>
  <programme name="PUB-CHAUSSURE-FASHION" start="00:52:04" end="00:53:57" url="youtube:yORIAPoLSAE"></programme>
  <programme name="GEN-PUB" start="00:56:57" end="00:57:35" url="youtube:lMTkpj62Vbg"></programme>
  <programme name="PUB-CHEMISE-FASHION" start="00:57:35" end="00:59:23" url="youtube:X0WGkOPLU5c"></programme>
  <programme name="GEN-MPAKA" start="00:59:23" end="01:00:00" url="youtube:e36xg4ThoJg"></programme>

</programmes>